KISSmetrics/__init__.py
KISSmetrics/client.py
KISSmetrics/client_compat.py
KISSmetrics/query_string.py
KISSmetrics/request.py
py_KISSmetrics-1.1.0.dist-info/LICENSE.txt
py_KISSmetrics-1.1.0.dist-info/METADATA
py_KISSmetrics-1.1.0.dist-info/WHEEL
py_KISSmetrics-1.1.0.dist-info/top_level.txt
py_KISSmetrics-1.1.0.dist-info/RECORD
