Metadata-Version: 2.1
Name: py-KISSmetrics
Version: 1.1.0
Summary: Official KISSmetrics client library.
Home-page: https://github.com/kissmetrics/py-KISSmetrics/
Author: Ernest W. Durbin III
Author-email: ewdurbin@gmail.com
License: MIT
Platform: UNKNOWN
Classifier: Environment :: Web Environment
Classifier: Intended Audience :: Developers
Classifier: License :: OSI Approved :: MIT License
Classifier: Operating System :: OS Independent
Classifier: Programming Language :: Python
Classifier: Programming Language :: Python :: 2
Classifier: Programming Language :: Python :: 3
Classifier: Topic :: Internet :: WWW/HTTP
Classifier: Topic :: Software Development :: Libraries
Requires-Dist: urllib3 (<2.0,>=1.2)
